{
  "routes": [
    {
      "method": "GET",
      "path": "/salads",
      "handler": "salads.find",
      "config": {
        "policies": []
      }
    },
    {
      "method": "GET",
      "path": "/salads/count",
      "handler": "salads.count",
      "config": {
        "policies": []
      }
    },
    {
      "method": "GET",
      "path": "/salads/:id",
      "handler": "salads.findOne",
      "config": {
        "policies": []
      }
    },
    {
      "method": "POST",
      "path": "/salads",
      "handler": "salads.create",
      "config": {
        "policies": []
      }
    },
    {
      "method": "PUT",
      "path": "/salads/:id",
      "handler": "salads.update",
      "config": {
        "policies": []
      }
    },
    {
      "method": "DELETE",
      "path": "/salads/:id",
      "handler": "salads.delete",
      "config": {
        "policies": []
      }
    }
  ]
}
